pgaddons/__init__.py
pgaddons/base_class.py
pgaddons/button.py
pgaddons/checkbox.py
pgaddons/errors.py
pgaddons/funcs.py
pgaddons/input_field.py
pgaddons/link.py
pgaddons/slider.py
pgaddons-1.2.1.dist-info/METADATA
pgaddons-1.2.1.dist-info/WHEEL
pgaddons-1.2.1.dist-info/licenses/LICENCE
pgaddons-1.2.1.dist-info/RECORD
