Metadata-Version: 2.4
Name: pgaddons
Version: 1.2.1
Summary: A collection of additions to pygame.
Project-URL: Homepage, https://github.com/iamdeedz/pygame-addons
Project-URL: Issues, https://github.com/iamdeedz/pygame-addons/issues
Author: iamdeedz
License: MIT License
License-File: LICENCE
Keywords: gui,pygame
Requires-Python: >=3
Requires-Dist: pygame
